edit_python_pe/__about__.py
edit_python_pe/__init__.py
edit_python_pe/constants.py
edit_python_pe/main.py
edit_python_pe/strings.py
edit_python_pe/utils.py
edit_python_pe-0.2.10.dist-info/METADATA
edit_python_pe-0.2.10.dist-info/WHEEL
edit_python_pe-0.2.10.dist-info/entry_points.txt
edit_python_pe-0.2.10.dist-info/licenses/LICENSE
edit_python_pe-0.2.10.dist-info/RECORD
