Metadata-Version: 2.4
Name: edit-python-pe
Version: 0.2.10
Summary: Allows member and project profile editing onto python.pe git repository
Project-URL: Homepage, http://github.com/pythonpe/edit-python.pe
Project-URL: Documentation, https://github.com/pythonpe/edit-python.pe/blob/main/README.md
Project-URL: Repository, http://github.com/pythonpe/edit-python.pe
Project-URL: Issues, https://github.com/pythonpe/edit-python.pe/issues
Author-email: Jean-Pierre Chauvel <jean.p.chauvel@gmail.com>
License:                                  Apache License
License-File: LICENSE
Classifier: Development Status :: 4 - Beta
Classifier: Intended Audience :: Developers
Classifier: Programming Language :: Python :: 3
Classifier: Programming Language :: Python :: 3.13
Classifier: Topic :: Documentation :: Sphinx
Requires-Python: >=3.13
Requires-Dist: babel==2.17.0
Requires-Dist: platformdirs==4.4.0
Requires-Dist: pygit2==1.18.2
Requires-Dist: pygithub==2.8.1
Requires-Dist: pyyaml==6.0.2
Requires-Dist: textual==6.1.0
